circuit-tracer-main/__init__.py
circuit-tracer-main/setup.py
circuit-tracer-main/circuit_tracer/__init__.py
circuit-tracer-main/circuit_tracer/__main__.py
circuit-tracer-main/circuit_tracer/attribution.py
circuit-tracer-main/circuit_tracer/graph.py
circuit-tracer-main/circuit_tracer/replacement_model.py
circuit-tracer-main/circuit_tracer/frontend/__init__.py
circuit-tracer-main/circuit_tracer/frontend/feature_models.py
circuit-tracer-main/circuit_tracer/frontend/graph_models.py
circuit-tracer-main/circuit_tracer/frontend/local_server.py
circuit-tracer-main/circuit_tracer/frontend/utils.py
circuit-tracer-main/circuit_tracer/transcoder/__init__.py
circuit-tracer-main/circuit_tracer/transcoder/activation_functions.py
circuit-tracer-main/circuit_tracer/transcoder/single_layer_transcoder.py
circuit-tracer-main/circuit_tracer/utils/__init__.py
circuit-tracer-main/circuit_tracer/utils/create_graph_files.py
circuit-tracer-main/circuit_tracer/utils/disk_offload.py
circuit-tracer-main/circuit_tracer/utils/hf_utils.py
circuit-tracer-main/demos/__init__.py
circuit-tracer-main/demos/graph_visualization.py
circuit-tracer-main/demos/utils.py
circuit-tracer-main/tests/__init__.py
circuit-tracer-main/tests/test_attributions_gemma.py
circuit-tracer-main/tests/test_attributions_llama.py
circuit-tracer-main/tests/test_graph.py
constitutional_dynamics/__init__.py
constitutional_dynamics/cfg/__init__.py
constitutional_dynamics/cfg/defaults.yaml
constitutional_dynamics/cfg/logging.yaml
constitutional_dynamics/cli/__init__.py
constitutional_dynamics/cli/main.py
constitutional_dynamics/core/__init__.py
constitutional_dynamics/core/metrics.py
constitutional_dynamics/core/optimise.py
constitutional_dynamics/core/space.py
constitutional_dynamics/core/transition.py
constitutional_dynamics/integrations/__init__.py
constitutional_dynamics/integrations/graph.py
constitutional_dynamics/integrations/quantum.py
constitutional_dynamics/integrations/strategist.py
constitutional_dynamics-0.2.0.dist-info/licenses/LICENSE
constitutional_dynamics-0.2.0.dist-info/METADATA
constitutional_dynamics-0.2.0.dist-info/WHEEL
constitutional_dynamics-0.2.0.dist-info/entry_points.txt
constitutional_dynamics-0.2.0.dist-info/top_level.txt
constitutional_dynamics-0.2.0.dist-info/RECORD
