Metadata-Version: 2.4
Name: constitutional-dynamics
Version: 0.2.0
Summary: Constitutional Dynamics: An application for AI alignment analysis using State Transition Calculus principles from the PrincipiaDynamica project
Home-page: https://github.com/FF-GardenFn/principiadynamica
Author: FF-GardenFn
Author-email: faycal.farhat@mail.mcgill.ca
Classifier: Development Status :: 3 - Alpha
Classifier: Intended Audience :: Science/Research
Classifier: License :: OSI Approved :: Apache Software License
Classifier: Programming Language :: Python :: 3
Classifier: Programming Language :: Python :: 3.8
Classifier: Programming Language :: Python :: 3.9
Classifier: Programming Language :: Python :: 3.10
Classifier: Programming Language :: Python :: 3.11
Classifier: Topic :: Scientific/Engineering :: Artificial Intelligence
Requires-Python: >=3.8
License-File: LICENSE
Requires-Dist: numpy
Requires-Dist: scipy
Requires-Dist: pyyaml
Requires-Dist: rich
Provides-Extra: graph
Requires-Dist: neo4j; extra == "graph"
Provides-Extra: quantum
Requires-Dist: dwave-ocean-sdk; extra == "quantum"
Provides-Extra: circuit-tracer
Requires-Dist: circuit_tracer; extra == "circuit-tracer"
Requires-Dist: torch; extra == "circuit-tracer"
Provides-Extra: dev
Requires-Dist: pytest; extra == "dev"
Requires-Dist: black; extra == "dev"
Requires-Dist: ruff; extra == "dev"
Dynamic: author
Dynamic: author-email
Dynamic: classifier
Dynamic: description
Dynamic: description-content-type
Dynamic: home-page
Dynamic: license-file
Dynamic: provides-extra
Dynamic: requires-dist
Dynamic: requires-python
Dynamic: summary
